{
    "key": "group_church_leader_fields",
    "title": "Church Leader Details",
    "fields": [
        {
            "key": "field_leader_roles",
            "label": "Leader Roles",
            "name": "leader_roles",
            "aria-label": "",
            "type": "taxonomy",
            "instructions": "Select all applicable roles for this church leader.",
            "required": 1,
            "conditional_logic": 0,
            "wrapper": {
                "width": "",
                "class": "",
                "id": ""
            },
            "taxonomy": "leader-role",
            "field_type": "checkbox",
            "add_term": 0,
            "save_terms": 1,
            "load_terms": 1,
            "return_format": "id",
            "multiple": 1,
            "allow_null": 0
        },
        {
            "key": "field_leader_general_accordion",
            "label": "General Information",
            "name": "",
            "aria-label": "",
            "type": "accordion",
            "instructions": "",
            "required": 0,
            "conditional_logic": 0,
            "wrapper": {
                "width": "",
                "class": "",
                "id": ""
            },
            "open": 1,
            "multi_expand": 1,
            "endpoint": 0
        },
        {
            "key": "field_leader_first_name",
            "label": "First Name",
            "name": "first_name",
            "aria-label": "",
            "type": "text",
            "instructions": "",
            "required": 0,
            "conditional_logic": 0,
            "wrapper": {
                "width": "33",
                "class": "",
                "id": ""
            },
            "default_value": "",
            "maxlength": "",
            "placeholder": "",
            "prepend": "",
            "append": ""
        },
        {
            "key": "field_leader_middle_name",
            "label": "Middle Name",
            "name": "middle_name",
            "aria-label": "",
            "type": "text",
            "instructions": "",
            "required": 0,
            "conditional_logic": 0,
            "wrapper": {
                "width": "33",
                "class": "",
                "id": ""
            },
            "default_value": "",
            "maxlength": "",
            "placeholder": "",
            "prepend": "",
            "append": ""
        },
        {
            "key": "field_leader_last_name",
            "label": "Last Name",
            "name": "last_name",
            "aria-label": "",
            "type": "text",
            "instructions": "",
            "required": 0,
            "conditional_logic": 0,
            "wrapper": {
                "width": "34",
                "class": "",
                "id": ""
            },
            "default_value": "",
            "maxlength": "",
            "placeholder": "",
            "prepend": "",
            "append": ""
        },
        {
            "key": "field_leader_birthdate",
            "label": "Birth Date",
            "name": "birthdate",
            "aria-label": "",
            "type": "date_picker",
            "instructions": "",
            "required": 0,
            "conditional_logic": 0,
            "wrapper": {
                "width": "50",
                "class": "",
                "id": ""
            },
            "display_format": "F j, Y",
            "return_format": "Y-m-d",
            "first_day": 0
        },
        {
            "key": "field_leader_deathdate",
            "label": "Death Date",
            "name": "deathdate",
            "aria-label": "",
            "type": "date_picker",
            "instructions": "Leave empty for living leaders.",
            "required": 0,
            "conditional_logic": 0,
            "wrapper": {
                "width": "50",
                "class": "",
                "id": ""
            },
            "display_format": "F j, Y",
            "return_format": "Y-m-d",
            "first_day": 0
        },
        {
            "key": "field_leader_hometown",
            "label": "Hometown",
            "name": "hometown",
            "aria-label": "",
            "type": "text",
            "instructions": "",
            "required": 0,
            "conditional_logic": 0,
            "wrapper": {
                "width": "",
                "class": "",
                "id": ""
            },
            "default_value": "",
            "maxlength": "",
            "placeholder": "",
            "prepend": "",
            "append": ""
        },
        {
            "key": "field_leader_background_accordion",
            "label": "Background",
            "name": "",
            "aria-label": "",
            "type": "accordion",
            "instructions": "",
            "required": 0,
            "conditional_logic": 0,
            "wrapper": {
                "width": "",
                "class": "",
                "id": ""
            },
            "open": 0,
            "multi_expand": 1,
            "endpoint": 0
        },
        {
            "key": "field_leader_education",
            "label": "Education",
            "name": "education",
            "aria-label": "",
            "type": "textarea",
            "instructions": "",
            "required": 0,
            "conditional_logic": 0,
            "wrapper": {
                "width": "",
                "class": "",
                "id": ""
            },
            "default_value": "",
            "maxlength": "",
            "rows": 3,
            "placeholder": "",
            "new_lines": ""
        },
        {
            "key": "field_leader_mission",
            "label": "Mission",
            "name": "mission",
            "aria-label": "",
            "type": "text",
            "instructions": "Mission served (e.g., \"England London\" or \"Brazil São Paulo\").",
            "required": 0,
            "conditional_logic": 0,
            "wrapper": {
                "width": "",
                "class": "",
                "id": ""
            },
            "default_value": "",
            "maxlength": "",
            "placeholder": "",
            "prepend": "",
            "append": ""
        },
        {
            "key": "field_leader_profession",
            "label": "Profession",
            "name": "profession",
            "aria-label": "",
            "type": "text",
            "instructions": "Career/profession before or during church service.",
            "required": 0,
            "conditional_logic": 0,
            "wrapper": {
                "width": "",
                "class": "",
                "id": ""
            },
            "default_value": "",
            "maxlength": "",
            "placeholder": "",
            "prepend": "",
            "append": ""
        },
        {
            "key": "field_leader_military",
            "label": "Military Service",
            "name": "military",
            "aria-label": "",
            "type": "text",
            "instructions": "",
            "required": 0,
            "conditional_logic": 0,
            "wrapper": {
                "width": "",
                "class": "",
                "id": ""
            },
            "default_value": "",
            "maxlength": "",
            "placeholder": "",
            "prepend": "",
            "append": ""
        },
        {
            "key": "field_leader_polygamy_accordion",
            "label": "Polygamy",
            "name": "",
            "aria-label": "",
            "type": "accordion",
            "instructions": "",
            "required": 0,
            "conditional_logic": 0,
            "wrapper": {
                "width": "",
                "class": "",
                "id": ""
            },
            "open": 0,
            "multi_expand": 1,
            "endpoint": 0
        },
        {
            "key": "field_leader_polygamist",
            "label": "Polygamist",
            "name": "polygamist",
            "aria-label": "",
            "type": "true_false",
            "instructions": "Was this leader a polygamist?",
            "required": 0,
            "conditional_logic": 0,
            "wrapper": {
                "width": "",
                "class": "",
                "id": ""
            },
            "message": "",
            "default_value": 0,
            "ui": 1,
            "ui_on_text": "",
            "ui_off_text": ""
        },
        {
            "key": "field_leader_number_of_wives",
            "label": "Number of Wives",
            "name": "number_of_wives",
            "aria-label": "",
            "type": "number",
            "instructions": "",
            "required": 0,
            "conditional_logic": [
                [
                    {
                        "field": "field_leader_polygamist",
                        "operator": "==",
                        "value": "1"
                    }
                ]
            ],
            "wrapper": {
                "width": "",
                "class": "",
                "id": ""
            },
            "default_value": "",
            "min": 1,
            "max": "",
            "placeholder": "",
            "step": "",
            "prepend": "",
            "append": ""
        },
        {
            "key": "field_leader_apostle_accordion",
            "label": "Apostle Information",
            "name": "",
            "aria-label": "",
            "type": "accordion",
            "instructions": "",
            "required": 0,
            "conditional_logic": 0,
            "wrapper": {
                "width": "",
                "class": "",
                "id": ""
            },
            "open": 1,
            "multi_expand": 1,
            "endpoint": 0
        },
        {
            "key": "field_leader_ordained_date",
            "label": "Ordained as Apostle",
            "name": "ordained_date",
            "aria-label": "",
            "type": "date_time_picker",
            "instructions": "Date and time ordained as an apostle. Time is optional - only needed when multiple apostles were ordained the same day to establish seniority order.",
            "required": 0,
            "conditional_logic": 0,
            "wrapper": {
                "width": "",
                "class": "",
                "id": ""
            },
            "display_format": "F j, Y g:i a",
            "return_format": "Y-m-d H:i:s",
            "first_day": 0
        },
        {
            "key": "field_leader_ordain_end",
            "label": "Service Ended",
            "name": "ordain_end",
            "aria-label": "",
            "type": "date_picker",
            "instructions": "Date apostolic service ended if not by death (e.g., excommunication, resignation, removal from quorum).",
            "required": 0,
            "conditional_logic": 0,
            "wrapper": {
                "width": "",
                "class": "",
                "id": ""
            },
            "display_format": "F j, Y",
            "return_format": "Y-m-d",
            "first_day": 0
        },
        {
            "key": "field_leader_ordain_note",
            "label": "Service End Note",
            "name": "ordain_note",
            "aria-label": "",
            "type": "textarea",
            "instructions": "Explanation for how apostolic service ended (excommunication, resignation, etc.) including dates of rebaptism if applicable.",
            "required": 0,
            "conditional_logic": 0,
            "wrapper": {
                "width": "",
                "class": "",
                "id": ""
            },
            "default_value": "",
            "maxlength": "",
            "rows": 3,
            "placeholder": "",
            "new_lines": "br"
        },
        {
            "key": "field_leader_prophet_accordion",
            "label": "Prophet/President Information",
            "name": "",
            "aria-label": "",
            "type": "accordion",
            "instructions": "",
            "required": 0,
            "conditional_logic": 0,
            "wrapper": {
                "width": "",
                "class": "",
                "id": ""
            },
            "open": 1,
            "multi_expand": 1,
            "endpoint": 0
        },
        {
            "key": "field_leader_became_president_date",
            "label": "Became Church President",
            "name": "became_president_date",
            "aria-label": "",
            "type": "date_picker",
            "instructions": "Date this leader became President of the Church.",
            "required": 0,
            "conditional_logic": 0,
            "wrapper": {
                "width": "",
                "class": "",
                "id": ""
            },
            "display_format": "F j, Y",
            "return_format": "Y-m-d",
            "first_day": 0
        },
        {
            "key": "field_leader_integration_accordion",
            "label": "Site Integration",
            "name": "",
            "aria-label": "",
            "type": "accordion",
            "instructions": "",
            "required": 0,
            "conditional_logic": 0,
            "wrapper": {
                "width": "",
                "class": "",
                "id": ""
            },
            "open": 0,
            "multi_expand": 1,
            "endpoint": 0
        },
        {
            "key": "field_leader_tag",
            "label": "Associated Tag",
            "name": "leader_tag",
            "aria-label": "",
            "type": "taxonomy",
            "instructions": "Link to existing WordPress tag for this leader (for migration from tag-based system).",
            "required": 0,
            "conditional_logic": 0,
            "wrapper": {
                "width": "",
                "class": "",
                "id": ""
            },
            "taxonomy": "post_tag",
            "field_type": "select",
            "allow_null": 1,
            "add_term": 0,
            "save_terms": 0,
            "load_terms": 0,
            "return_format": "id",
            "multiple": 0
        },
        {
            "key": "field_leader_end_accordion",
            "label": "End",
            "name": "",
            "aria-label": "",
            "type": "accordion",
            "instructions": "",
            "required": 0,
            "conditional_logic": 0,
            "wrapper": {
                "width": "",
                "class": "",
                "id": ""
            },
            "open": 0,
            "multi_expand": 0,
            "endpoint": 1
        }
    ],
    "location": [
        [
            {
                "param": "post_type",
                "operator": "==",
                "value": "church-leader"
            }
        ]
    ],
    "menu_order": 0,
    "position": "normal",
    "style": "default",
    "label_placement": "top",
    "instruction_placement": "label",
    "hide_on_screen": "",
    "active": true,
    "description": "Fields for the Church Leader custom post type.",
    "show_in_rest": 0,
    "modified": 1736812800
}